README.md
setup.py
BonziBuddy/__init__.py
BonziBuddy.egg-info/PKG-INFO
BonziBuddy.egg-info/SOURCES.txt
BonziBuddy.egg-info/dependency_links.txt
BonziBuddy.egg-info/entry_points.txt
BonziBuddy.egg-info/requires.txt
BonziBuddy.egg-info/top_level.txt