Metadata-Version: 2.1
Name: BonziBuddy
Version: 1.0
Summary: A Smaller Version Of Great BonziBuddy In Pure Python..
Home-page: https://github.com/BLUE-DEVIL1134/BonziBuddy
Author: Akash Pattnaik
Author-email: akashpattnaik.github@gmail.com
License: MIT
Platform: UNKNOWN
Classifier: License :: OSI Approved :: MIT License
Classifier: Programming Language :: Python :: 3.5
Classifier: Programming Language :: Python :: 3.6
Classifier: Programming Language :: Python :: 3.7
Classifier: Programming Language :: Python :: 3.8
Classifier: Operating System :: Microsoft :: Windows
